print_linkdings.py
print_linkdings-0.1.dist-info/METADATA
print_linkdings-0.1.dist-info/WHEEL
print_linkdings-0.1.dist-info/entry_points.txt
print_linkdings-0.1.dist-info/licenses/LICENSE
print_linkdings-0.1.dist-info/RECORD
