Metadata-Version: 2.3
Name: print-linkdings
Version: 0.1
Summary: Print links from Linkding bookmarks including those one hop away.
Project-URL: Homepage, https://codeberg.org/hyperreal/print-linkdings
Project-URL: Issues, https://codeberg.org/hyperreal/print-linkdings/issues
Author-email: Jeffrey Serio <hyperreal@fedoraproject.org>
Classifier: License :: OSI Approved :: GNU General Public License v3 or later (GPLv3+)
Classifier: Operating System :: OS Independent
Classifier: Programming Language :: Python :: 3
Requires-Python: >=3.10
Requires-Dist: courlan>=1.3.2
Requires-Dist: requests>=2.32.3
